{
  "version": "7",
  "dialect": "postgresql",
  "entries": [
    {
      "idx": 0,
      "version": "7",
      "when": 1756292534750,
      "tag": "0000_redundant_goblin_queen",
      "breakpoints": true
    },
    {
      "idx": 1,
      "version": "7",
      "when": 1756293491819,
      "tag": "0001_breezy_fantastic_four",
      "breakpoints": true
    },
    {
      "idx": 2,
      "version": "7",
      "when": 1756382343077,
      "tag": "0002_cuddly_sebastian_shaw",
      "breakpoints": true
    },
    {
      "idx": 3,
      "version": "7",
      "when": 1756382481719,
      "tag": "0003_cooing_blink",
      "breakpoints": true
    },
    {
      "idx": 4,
      "version": "7",
      "when": 1757288414368,
      "tag": "0004_natural_shiver_man",
      "breakpoints": true
    }
  ]
}